Metadata-Version: 2.1
Name: kecpkg-tools
Version: 1.1.0
Home-page: https://github.com/jberends/kecpkg-tools
Author: Jochem Berends
Author-email: jochem.berends@ke-works.com
Maintainer: Jochem Berends
Maintainer-email: jochem.berends@ke-works.com
License: Apache-2.0
Keywords: python,package tools,pykechain,KE-chain,Services Integration Module,SIM,KECPKG,GPG
Classifier: Development Status :: 5 - Production/Stable
Classifier: Intended Audience :: Developers
Classifier: License :: OSI Approved :: Apache Software License
Classifier: Natural Language :: English
Classifier: Operating System :: OS Independent
Classifier: Programming Language :: Python :: 3.7
Classifier: Programming Language :: Python :: 3.8
Classifier: Programming Language :: Python :: 3.9
Classifier: Programming Language :: Python :: 3.10
Classifier: Programming Language :: Python :: 3.11
Classifier: Programming Language :: Python :: 3.12
Classifier: Programming Language :: Python :: Implementation :: CPython
Classifier: Programming Language :: Python :: Implementation :: PyPy
License-File: LICENSE
Requires-Dist: click
Requires-Dist: atomicwrites
Requires-Dist: jinja2
Requires-Dist: pykechain >=3.0
Requires-Dist: appdirs
Requires-Dist: tabulate
Requires-Dist: python-gnupg
